stockoption/__init__.py
stockoption/_constants.py
stockoption/pricing.py
stockoption-1.0.10.dist-info/LICENSE
stockoption-1.0.10.dist-info/METADATA
stockoption-1.0.10.dist-info/WHEEL
stockoption-1.0.10.dist-info/top_level.txt
stockoption-1.0.10.dist-info/RECORD
